odoo8_addon_runbot_build_instructions-8.0.1.3.0.99.dev7-py2.7-nspkg.pth
odoo8_addon_runbot_build_instructions-8.0.1.3.0.99.dev7.dist-info/METADATA
odoo8_addon_runbot_build_instructions-8.0.1.3.0.99.dev7.dist-info/RECORD
odoo8_addon_runbot_build_instructions-8.0.1.3.0.99.dev7.dist-info/WHEEL
odoo8_addon_runbot_build_instructions-8.0.1.3.0.99.dev7.dist-info/namespace_packages.txt
odoo8_addon_runbot_build_instructions-8.0.1.3.0.99.dev7.dist-info/top_level.txt
odoo_addons/runbot_build_instructions/README.rst
odoo_addons/runbot_build_instructions/__init__.py
odoo_addons/runbot_build_instructions/__openerp__.py
odoo_addons/runbot_build_instructions/runbot_build.py
odoo_addons/runbot_build_instructions/runbot_repo.py
odoo_addons/runbot_build_instructions/runbot_repo_view.xml
odoo_addons/runbot_build_instructions/static/description/icon.png
