Metadata-Version: 2.1
Name: odoo8-addon-runbot-build-instructions
Version: 8.0.1.3.0.99.dev7
Summary: Runbot with custom build and run instructions
Home-page: UNKNOWN
Author: Savoir-faire Linux,Odoo Community Association (OCA)
Author-email: support@odoo-community.org
License: UNKNOWN
Platform: UNKNOWN
Classifier: Programming Language :: Python
Classifier: Framework :: Odoo
Requires-Python: ~=2.7
Requires-Dist: odoo8-addon-runbot
Requires-Dist: odoo (<9.0a,>=8.0a)
